RsCmwEvdoSig/RsCmwEvdoSig.py
RsCmwEvdoSig/__init__.py
RsCmwEvdoSig/enums.py
RsCmwEvdoSig/repcap.py
RsCmwEvdoSig/CustomFiles/__init__.py
RsCmwEvdoSig/CustomFiles/events.py
RsCmwEvdoSig/CustomFiles/reliability.py
RsCmwEvdoSig/CustomFiles/utilities.py
RsCmwEvdoSig/Implementations/Call.py
RsCmwEvdoSig/Implementations/Configure.py
RsCmwEvdoSig/Implementations/Cswitched.py
RsCmwEvdoSig/Implementations/Pdata.py
RsCmwEvdoSig/Implementations/Per.py
RsCmwEvdoSig/Implementations/Route.py
RsCmwEvdoSig/Implementations/RxQuality.py
RsCmwEvdoSig/Implementations/Sense.py
RsCmwEvdoSig/Implementations/Source.py
RsCmwEvdoSig/Implementations/Throughput.py
RsCmwEvdoSig/Implementations/__init__.py
RsCmwEvdoSig/Implementations/Call_/Cswitched.py
RsCmwEvdoSig/Implementations/Call_/Handoff.py
RsCmwEvdoSig/Implementations/Call_/__init__.py
RsCmwEvdoSig/Implementations/Configure_/Application.py
RsCmwEvdoSig/Implementations/Configure_/Carrier.py
RsCmwEvdoSig/Implementations/Configure_/Connection.py
RsCmwEvdoSig/Implementations/Configure_/Cstatus.py
RsCmwEvdoSig/Implementations/Configure_/Fading.py
RsCmwEvdoSig/Implementations/Configure_/Handoff.py
RsCmwEvdoSig/Implementations/Configure_/IqIn.py
RsCmwEvdoSig/Implementations/Configure_/Layer.py
RsCmwEvdoSig/Implementations/Configure_/Mac.py
RsCmwEvdoSig/Implementations/Configure_/Mmonitor.py
RsCmwEvdoSig/Implementations/Configure_/Ncell.py
RsCmwEvdoSig/Implementations/Configure_/Network.py
RsCmwEvdoSig/Implementations/Configure_/Pilot.py
RsCmwEvdoSig/Implementations/Configure_/RfPower.py
RsCmwEvdoSig/Implementations/Configure_/RfSettings.py
RsCmwEvdoSig/Implementations/Configure_/RpControl.py
RsCmwEvdoSig/Implementations/Configure_/RxQuality.py
RsCmwEvdoSig/Implementations/Configure_/Sector.py
RsCmwEvdoSig/Implementations/Configure_/System.py
RsCmwEvdoSig/Implementations/Configure_/Test.py
RsCmwEvdoSig/Implementations/Configure_/__init__.py
RsCmwEvdoSig/Implementations/Configure_/Carrier_/Level.py
RsCmwEvdoSig-3.8.10.17.dist-info/METADATA
RsCmwEvdoSig-3.8.10.17.dist-info/WHEEL
RsCmwEvdoSig-3.8.10.17.dist-info/top_level.txt
RsCmwEvdoSig-3.8.10.17.dist-info/RECORD
